Metadata-Version: 2.4
Name: thesis-py
Version: 1.0.2
Summary: Python SDK for Thesis.io APIs.
Home-page: https://github.com/oraichain/thesis-py
Author: Oraichain Labs
Author-email: Oraichain Labs <duc@orai.io>
License: GNU General Public License v3.0
Requires-Python: >=3.9
License-File: LICENSE
Requires-Dist: requests>=2.32.3
Requires-Dist: typing-extensions>=4.12.2
Requires-Dist: openai>=1.48
Requires-Dist: pydantic>=2.10.6
Requires-Dist: httpx>=0.28.1
Requires-Dist: httpcore>=1.0.9
Requires-Dist: python-dotenv>=1.0.1
Requires-Dist: litellm
Dynamic: author
Dynamic: home-page
Dynamic: license-file
